LenzPy/LenzPy.py
LenzPy/__init__.py
LenzPy-0.1.1.dist-info/METADATA
LenzPy-0.1.1.dist-info/WHEEL
LenzPy-0.1.1.dist-info/top_level.txt
LenzPy-0.1.1.dist-info/RECORD
