Metadata-Version: 2.1
Name: LenzPy
Version: 0.1.1
Summary: Python wrapper designed to facilitate interaction with the Lenz report API.
Home-page: https://github.com/GetLenz/LenzPy
